avajana/__init__.py
avajana/bubbling.py
avajana-0.4.1.dist-info/LICENSE.md
avajana-0.4.1.dist-info/WHEEL
avajana-0.4.1.dist-info/METADATA
avajana-0.4.1.dist-info/RECORD
